sqlalchemy_django_query.py
sqlalchemy_django_query-0.2.2.dist-info/LICENSE
sqlalchemy_django_query-0.2.2.dist-info/WHEEL
sqlalchemy_django_query-0.2.2.dist-info/METADATA
sqlalchemy_django_query-0.2.2.dist-info/RECORD
