Metadata-Version: 2.1
Name: sqlalchemy-django-query
Version: 0.2.2
Summary: A module that implements a more Django like interface for SQLAlchemy
Author: Armin Ronacher, Mike Bayer
Maintainer: Martín Gaitán, Artur Mruk
Requires-Python: >=3.7
Classifier: Programming Language :: Python :: 3
Requires-Dist: SQLAlchemy<1.4
Requires-Dist: pytest ; extra == "dev"
Requires-Dist: black ; extra == "dev"
Project-URL: Source, https://github.com/mgaitan/sqlalchemy-django-query
Provides-Extra: dev
